[
    {
        "Node": {
            "Element": {
                "id": "02c3e303-a443-4f02-9927-e43519227ade",
                "name": {
                    "Danish": "12. FUNDAMENTER",
                    "English": "",
                    "German": ""
                },
                "source": "User",
                "comment": "Created by Excel_to_JSON_LCAByg. https://github.com/Curiosit/Excel_to_JSON_LCAByg",
                "enabled": true,
                "active": true
            }
        }
    },
    {
        "Node": {
            "Element": {
                "id": "2deda828-166b-4470-be20-f5a773f49e91",
                "name": {
                    "Danish": "13. TERR\u00c6ND\u00c6K",
                    "English": "",
                    "German": ""
                },
                "source": "User",
                "comment": "Created by Excel_to_JSON_LCAByg. https://github.com/Curiosit/Excel_to_JSON_LCAByg",
                "enabled": true,
                "active": true
            }
        }
    },
    {
        "Node": {
            "Element": {
                "id": "a8aa98f4-6ba8-447b-8531-a38b4d358475",
                "name": {
                    "Danish": "21. YDERV\u00c6GGE",
                    "English": "",
                    "German": ""
                },
                "source": "User",
                "comment": "Created by Excel_to_JSON_LCAByg. https://github.com/Curiosit/Excel_to_JSON_LCAByg",
                "enabled": true,
                "active": true
            }
        }
    },
    {
        "Edge": [
            {
                "ElementToConstruction": {
                    "id": "20bc515c-9480-4492-9baa-1a80c9fff9b9",
                    "amount": 231789,
                    "enabled": true
                }
            },
            "a8aa98f4-6ba8-447b-8531-a38b4d358475",
            "d528f141-de5e-43c6-9e59-07d6a6f0fe86"
        ]
    },
    {
        "Edge": [
            {
                "ElementToConstruction": {
                    "id": "4182cbd2-1b55-48e1-a349-6251ea6474c5",
                    "amount": 25,
                    "enabled": true
                }
            },
            "a8aa98f4-6ba8-447b-8531-a38b4d358475",
            "c4c978bd-dd03-4410-8837-f9f5020bc7ba"
        ]
    },
    {
        "Node": {
            "Element": {
                "id": "c12d2830-f8f8-4eca-ad9e-27584c4d0425",
                "name": {
                    "Danish": "22. INDERV\u00c6GGE",
                    "English": "",
                    "German": ""
                },
                "source": "User",
                "comment": "Created by Excel_to_JSON_LCAByg. https://github.com/Curiosit/Excel_to_JSON_LCAByg",
                "enabled": true,
                "active": true
            }
        }
    },
    {
        "Node": {
            "Element": {
                "id": "7cc3b392-760f-49f9-a649-975c85b0cc4b",
                "name": {
                    "Danish": "23. ETAGED\u00c6K",
                    "English": "",
                    "German": ""
                },
                "source": "User",
                "comment": "Created by Excel_to_JSON_LCAByg. https://github.com/Curiosit/Excel_to_JSON_LCAByg",
                "enabled": true,
                "active": true
            }
        }
    },
    {
        "Node": {
            "Element": {
                "id": "f0e24e08-d3d0-4e7a-a38b-37b9df75555f",
                "name": {
                    "Danish": "27. TAGE",
                    "English": "",
                    "German": ""
                },
                "source": "User",
                "comment": "Created by Excel_to_JSON_LCAByg. https://github.com/Curiosit/Excel_to_JSON_LCAByg",
                "enabled": true,
                "active": true
            }
        }
    },
    {
        "Node": {
            "Element": {
                "id": "22fab3aa-d9fb-4297-88f4-ddf59728140c",
                "name": {
                    "Danish": "31. YDERV\u00c6GGE, KOMPLETTERING",
                    "English": "",
                    "German": ""
                },
                "source": "User",
                "comment": "Created by Excel_to_JSON_LCAByg. https://github.com/Curiosit/Excel_to_JSON_LCAByg",
                "enabled": true,
                "active": true
            }
        }
    },
    {
        "Node": {
            "Element": {
                "id": "4092bb5c-30f4-4318-a2e4-f4263346cdc9",
                "name": {
                    "Danish": "43. GULVE",
                    "English": "",
                    "German": ""
                },
                "source": "User",
                "comment": "Created by Excel_to_JSON_LCAByg. https://github.com/Curiosit/Excel_to_JSON_LCAByg",
                "enabled": true,
                "active": true
            }
        }
    },
    {
        "Node": {
            "Element": {
                "id": "76909908-e609-45da-bfae-793d5e132dec",
                "name": {
                    "Danish": "45. LOFTER",
                    "English": "",
                    "German": ""
                },
                "source": "User",
                "comment": "Created by Excel_to_JSON_LCAByg. https://github.com/Curiosit/Excel_to_JSON_LCAByg",
                "enabled": true,
                "active": true
            }
        }
    }
]